fundor_utilities/__init__.py
fundor_utilities/admin.py
fundor_utilities/apps.py
fundor_utilities/exception.py
fundor_utilities/markdown_extensions.py
fundor_utilities/migrations/__init__.py
fundor_utilities/models.py
fundor_utilities/permissions.py
fundor_utilities/templates/swagger-ui.html
fundor_utilities/templatetags/__init__.py
fundor_utilities/templatetags/fundor_tags.py
fundor_utilities/views/__init__.py
fundor_utilities/views/markdown_view.py
fundor_utilities/views/multiform/__init__.py
fundor_utilities/views/multiform/multiform_mixin.py
fundor_utilities/views/multiform/multiform_process.py
fundor_utilities/views/multiform/multiform_view.py
fundor_utilities/views/swagger/__init__.py
fundor_utilities/views/swagger/swagger_openapi.py
fundor_utilities/views/swagger/swagger_template_view.py
fundor_utilities/views/tcs_view.py
fundor_utilities/views/xlsx_view.py
fundor_utilities-4.1.2.dist-info/LICENSE
fundor_utilities-4.1.2.dist-info/METADATA
fundor_utilities-4.1.2.dist-info/WHEEL
fundor_utilities-4.1.2.dist-info/RECORD
