Metadata-Version: 2.3
Name: fundor_utilities
Version: 4.1.2
Summary: 
License: CC BY-NC-SA 4.0
Keywords: django,utilities
Author: Fundor333
Author-email: github@fundor333.com
Requires-Python: >=3.12, <4.0
Classifier: Development Status :: 5 - Production/Stable
Classifier: Environment :: Web Environment
Classifier: Framework :: Django
Classifier: Framework :: Django :: 3.0
Classifier: Intended Audience :: Developers
Classifier: Operating System :: OS Independent
Classifier: Programming Language :: Python
Classifier: Programming Language :: Python :: 3
Classifier: Programming Language :: Python :: 3.8
Classifier: Programming Language :: Python :: 3.9
Classifier: Programming Language :: Python :: 3.10
Classifier: Programming Language :: Python :: 3 :: Only
Classifier: Topic :: Internet :: WWW/HTTP
Requires-Dist: deprecation (>=2.1.0,<3.0.0)
Requires-Dist: django (>=5.0)
Requires-Dist: django-csv-export (>=0.0.3)
Requires-Dist: djangorestframework (>=3.16.0)
Requires-Dist: markdown (>=3.7,<4.0)
Requires-Dist: openpyxl (>=3.1.5,<4.0.0)
Project-URL: Homepage, https://github.com/fundor333/fundor_utilities
Project-URL: Repository, https://github.com/fundor333/fundor_utilities
